<?xml version="1.0" encoding="UTF-8" standalone="yes"?>
<node artifactManager="be.nabu.eai.module.rest.provider.RESTServiceManager" created="2023-04-20T10:02:26.133+02:00" lastModified="2024-08-14T15:41:35.731+02:00" leaf="true" version="75">
    <environmentId>apollo</environmentId>
    <hidden>false</hidden>
    <locked>false</locked>
    <properties/>
    <references>nabu.frameworks.datastore.Services.store</references>
    <references>nabu.utils.Runtime.summarizeException</references>
    <references>nabu.services.jdbc.Services.selectDynamic</references>
    <references>java.util.Date</references>
    <references>nabu.utils.types.ParameterDescription</references>
    <references>nabu.utils.reflection.Type.describe</references>
    <references>nabu.cms.translation.manage.crud.translationTransport.types.output</references>
    <references>nabu.cms.translation.manage.crud.translationTransportTopic.services.list</references>
    <references>nabu.cms.translation.manage.transport.runInput</references>
    <references>nabu.cms.translation.manage.crud.translationTransportInstance.services.create</references>
    <references>java.net.URI</references>
    <references>nabu.cms.translation.manage.crud.translationTransport.services.list</references>
    <references>nabu.data.json.Services.unmarshal</references>
    <references>nabu.utils.Properties.toObject</references>
    <references>nabu.utils.Date.now</references>
    <references>nabu.utils.String.toStream</references>
    <references>nabu.cms.translation.manage.crud.translationTermInstance.services.list</references>
    <references>nabu.cms.translation.specs.finalizedTranslation</references>
    <references>nabu.cms.translation.manage.transport.runOutput</references>
    <references>nabu.web.core.manage.reflection.propertyList</references>
    <references>nabu.services.jdbc.Services.update</references>
    <references>nabu.cms.translation.manage.crud.translationTermInstance.types.output</references>
    <references>java.lang.Object</references>
    <references>nabu.cms.translation.specs.transport</references>
    <references>nabu.cms.translation.manage.term.topicSql</references>
</node>
